{
"user_query":"As a small business owner, I'm looking for help in creating catchy slogans and taglines for my brand.",
"domain":"Technology",
"TaskList": [
{
"id": 1,
"description": "Conduct research on the brand's target audience to understand their preferences and values.",
"domain": "technology",
"required_inputs": ["brand_info", "target_audience_details"]
},
{
"id": 2,
"description": "Analyze competitors' slogans and taglines to identify trends and effective language.",
"domain": "technology",
"required_inputs": ["competitor_info"]
},
{
"id": 3,
"description": "Generate a list of creative slogan and tagline suggestions based on the research and analysis from previous steps.",
"domain": "technology",
"required_inputs": ["audience_preferences", "competitor_analysis"]
},
{
"id": 4,
"description": "Review and refine the generated slogans and taglines based on feedback from the target audience.",
"domain": "technology",
"required_inputs": ["slogan_list", "feedback"]
}
]
}