{
"user_query":"I'm writing an educational article about the significance of numbers, dates, and math in our daily lives. Can you provide me with interesting trivia facts about numbers, a historical event on a specific date, and a mathematical property? Additionally, fetch some relevant statistics about NBA players and their games to illustrate real-life examples.",
"domain":"Technology",
"TaskList": [
    {
        "id": 1,
        "description": "Fetch interesting trivia facts about numbers.",
        "domain": "technology",
        "required_inputs": []
    },
    {
        "id": 2,
        "description": "Retrieve a historical event that occurred on a specific date.",
        "domain": "technology",
        "required_inputs": ["specific_date"]
    },
    {
        "id": 3,
        "description": "Provide a mathematical property that is commonly used.",
        "domain": "technology",
        "required_inputs": []
    },
    {
        "id": 4,
        "description": "Collect relevant statistics about NBA players and their games.",
        "domain": "technology",
        "required_inputs": []
    }
]
}