{
"user_query":"Could you please assist me in finding the carbon footprint of using a classic bus for a 1000 km journey? Additionally, I would like to know the guidelines for medical treatments.",
"domain":"Technology, Medical",
"TaskList": [
    {
        "id": 1,
        "description": "Calculate the carbon footprint based on the distance and type of bus used.",
        "domain": "technology",
        "required_inputs": ["distance_in_km", "bus_type"]
    },
    {
        "id": 2,
        "description": "Retrieve guidelines for medical treatments.",
        "domain": "medical",
        "required_inputs": ["treatment_type"]
    }
]
}