{
"user_query":"I'm organizing a company event and I want to make it environmentally friendly. Can you recommend sustainable venues and transportation options for attendees? Also, provide me with the carbon footprint of the event and suggest eco-friendly catering services.",
"domain":"Cross-Domain",
"TaskList": [
{
"id": 1,
"description": "Research and list sustainable venues suitable for corporate events in the desired location.",
"domain": "Cross-Domain",
"required_inputs": ["event_location", "event_capacity", "event_date"]
},
{
"id": 2,
"description": "Find environmentally friendly transportation options for the attendees to the event venue.",
"domain": "Cross-Domain",
"required_inputs": ["event_location", "number_of_attendees"]
},
{
"id": 3,
"description": "Calculate the estimated carbon footprint of the event based on the venue, transportation, and catering options.",
"domain": "Cross-Domain",
"required_inputs": ["venue_details", "transportation_options", "number_of_attendees", "catering_options"]
},
{
"id": 4,
"description": "Identify eco-friendly catering services that align with sustainability goals for the event.",
"domain": "Cross-Domain",
"required_inputs": ["event_date", "event_location", "number_of_guests"]
}
]
}