{
"user_query":"I want to surprise my sister with a unique gift for her graduation. Can you give me a random fact about the number 2021? Also, I need to know the exchange rate from EUR to USD to determine the budget for her gift. Furthermore, please provide me with the stats of her favorite basketball team.",
"domain":"Cross-Domain",
"TaskList": [
{
"id": 1,
"description": "Get a random fact about the number 2021.",
"domain": "technology",
"required_inputs": []
},
{
"id": 2,
"description": "Retrieve the current exchange rate from EUR to USD.",
"domain": "finance",
"required_inputs": []
},
{
"id": 3,
"description": "Fetch stats for the user's favorite basketball team.",
"domain": "technology",
"required_inputs": ["team_name"]
}
]
}