{
"user_query":"I'm hosting a dinner party and I want to impress my guests with a unique menu.",
"domain":"Medical",
"TaskList": [
{
"id": 1,
"description": "Gather ideas for unique vegetarian dishes suitable for a dinner party.",
"domain": "medical",
"required_inputs": ["number_of_dishes", "cuisine_type", "difficulty_level"]
},
{
"id": 2,
"description": "Find a list of breweries in the area that offer vegetarian-friendly food.",
"domain": "medical",
"required_inputs": ["location", "radius"]
},
{
"id": 3,
"description": "Suggest cocktail pairings for the selected vegetarian dishes.",
"domain": "medical",
"required_inputs": ["selected_dishes"]
}
]
}