{
"user_query":"I want to organize a charity run and gather air quality information and nearby healthcare facilities.",
"domain":"Medical",
"TaskList": [
{
"id": 1,
"description": "Retrieve the air quality health index for the specified date of the charity run.",
"domain": "medical",
"required_inputs": ["event_date"]
},
{
"id": 2,
"description": "Identify and recommend nearby healthcare facilities suitable for emergencies during the charity run.",
"domain": "medical",
"required_inputs": ["event_location", "event_date"]
}
]
}