{
"user_query":"I want to get the stats for a horse named ZANAHIYR and the trainers' win rate in the last 7 days.",
"domain":"Finance",
"TaskList": [
    {
        "id": 1,
        "description": "Fetch the statistics for the horse named ZANAHIYR.",
        "domain": "finance",
        "required_inputs": ["horse_name"]
    },
    {
        "id": 2,
        "description": "Retrieve the trainers' win rate in the last 7 days.",
        "domain": "finance",
        "required_inputs": ["time_period", "trainer_id"]
    }
]
}