{
"user_query":"I want to invest in real estate and get advice on houses in Los Angeles and San Francisco, and search for related applications.",
"domain":"Finance",
"TaskList": [
    {
        "id": 1,
        "description": "Query information about houses available in Los Angeles.",
        "domain": "finance",
        "required_inputs": ["location: Los Angeles"]
    },
    {
        "id": 2,
        "description": "Query information about houses available in San Francisco.",
        "domain": "finance",
        "required_inputs": ["location: San Francisco"]
    },
    {
        "id": 3,
        "description": "Search for applications related to real estate.",
        "domain": "finance",
        "required_inputs": ["search_query: real estate"]
    }
]
}