{
"user_query":"I'm planning a trip to the United States and I want to explore the market trends in the US stock exchanges. Can you provide me with the most active stocks, gainers, and losers in the US? Additionally, I would like to know the price, charts, and news for a specific stock, ABNB:NASDAQ.",
"domain":"Finance",
"TaskList": [
{
"id": 1,
"description": "Retrieve the most active stocks in the US stock exchanges.",
"domain": "finance",
"required_inputs": []
},
{
"id": 2,
"description": "Retrieve the top gainers in the US stock exchanges.",
"domain": "finance",
"required_inputs": []
},
{
"id": 3,
"description": "Retrieve the top losers in the US stock exchanges.",
"domain": "finance",
"required_inputs": []
},
{
"id": 4,
"description": "Fetch the price, charts, and news for the stock ABNB:NASDAQ.",
"domain": "finance",
"required_inputs": ["stock_symbol"]
}
]
}