{
"user_query":"I am considering investing in cryptocurrencies and I need to validate the IBAN numbers for my bank accounts in different countries. Can you validate the IBAN numbers for the Netherlands, Belgium, and Luxembourg? Additionally, provide me with the 24 hours trading data for the cryptocurrency market on QuantaEx.",
"domain":"Finance",
"TaskList": [
    {
        "id": 1,
        "description": "Validate the IBAN number for the Netherlands.",
        "domain": "finance",
        "required_inputs": ["IBAN_Netherlands"]
    },
    {
        "id": 2,
        "description": "Validate the IBAN number for Belgium.",
        "domain": "finance",
        "required_inputs": ["IBAN_Belgium"],
        "dependencies": [1]
    },
    {
        "id": 3,
        "description": "Validate the IBAN number for Luxembourg.",
        "domain": "finance",
        "required_inputs": ["IBAN_Luxembourg"],
        "dependencies": [2]
    },
    {
        "id": 4,
        "description": "Fetch the 24 hours trading data for the cryptocurrency market on QuantaEx.",
        "domain": "finance",
        "required_inputs": []
    }
]
}