{
"user_query":"I want to analyze the performance of my portfolio.",
"domain":"Finance",
"TaskList": [
{
"id": 1,
"description": "Fetch portfolio information for portfolio ID 123456.",
"domain": "finance",
"required_inputs": ["portfolio ID"]
},
{
"id": 2,
"description": "Fetch the latest stock prices for Apple Inc.",
"domain": "finance",
"required_inputs": ["stock symbol"]
},
{
"id": 3,
"description": "Fetch the latest stock prices for Tesla Inc.",
"domain": "finance",
"required_inputs": ["stock symbol"]
}
]
}