{
"user_query":"I'm writing an article about the correlation between market sentiment and website traffic.",
"domain":"Finance",
"TaskList": [
{
"id": 1,
"description": "Fetch the Fear and Greed index for the past month to analyze market sentiment.",
"domain": "finance",
"required_inputs": ["timeframe", "index_type"]
},
{
"id": 2,
"description": "Retrieve the visit data for google.com over the same period (past month).",
"domain": "technology",
"required_inputs": ["domain_name", "timeframe"]
},
{
"id": 3,
"description": "Analyze the correlation between the Fear and Greed index and the visit data from google.com.",
"domain": "finance",
"required_inputs": ["fear_and_greed_data", "visit_data"]
}
]
}