{
"user_query":"My friend is planning a hiking trip to the Grand Canyon. Can you provide the air quality forecast for the next three days in that area? Also, recommend some hiking trails nearby. Additionally, provide a simple radiation forecast for the same period.",
"domain":"Tourism",
"TaskList": [
    {
        "id": 1,
        "description": "Fetch the air quality forecast for the Grand Canyon for the next three days.",
        "domain": "tourism",
        "required_inputs": ["location: Grand Canyon", "duration: 3 days"]
    },
    {
        "id": 2,
        "description": "Recommend hiking trails nearby the Grand Canyon.",
        "domain": "tourism",
        "required_inputs": ["location: Grand Canyon"]
    },
    {
        "id": 3,
        "description": "Fetch the radiation forecast for the Grand Canyon for the next three days.",
        "domain": "tourism",
        "required_inputs": ["location: Grand Canyon", "duration: 3 days"]
    }
]
}