{
"user_query":"I need to organize a surprise birthday party for my best friend.",
"domain":"Tourism",
"TaskList": [
    {
        "id": 1,
        "description": "Find a venue in downtown Seattle that can accommodate around 50 people.",
        "domain": "tourism",
        "required_inputs": ["location", "capacity"]
    },
    {
        "id": 2,
        "description": "Provide a list of local bakeries that offer custom birthday cakes with delivery service.",
        "domain": "tourism",
        "required_inputs": ["location", "cake_customization", "delivery_option"]
    },
    {
        "id": 3,
        "description": "Suggest some fun activities or games that can be organized during the party.",
        "domain": "tourism",
        "required_inputs": ["party_theme", "guest_demographics"]
    }
]
}