{
"user_query":"I want to plan a vacation to a tropical island including snorkeling spots and hotels.",
"domain":"Tourism",
"TaskList": [
    {
        "id": 1,
        "description": "Retrieve the geocoordinates for the best snorkeling spots on the tropical island.",
        "domain": "travel",
        "required_inputs": ["island_name", "activity_type"]
    },
    {
        "id": 2,
        "description": "Find nearby hotels based on the location of the snorkeling spots.",
        "domain": "travel",
        "required_inputs": ["snorkeling_spot_coordinates"]
    },
    {
        "id": 3,
        "description": "Get the address for the nearest beach to the selected hotel.",
        "domain": "travel",
        "required_inputs": ["hotel_location_coordinates"]
    }
]
}