{
"user_query":"I'm planning a trip to Paris next month and I want to explore the city's culinary scene. Can you recommend some popular restaurants in Paris? Additionally, I'd like to know the translation of the word 'delicious' from English to French. Also, provide me with some interesting trivia facts about the number 42.",
"domain":"Tourism",
"TaskList": [
    {
        "id": 1,
        "description": "Gather a list of popular restaurants in Paris.",
        "domain": "tourism",
        "required_inputs": []
    },
    {
        "id": 2,
        "description": "Translate the word 'delicious' from English to French.",
        "domain": "technology",
        "required_inputs": ["word_to_translate"]
    },
    {
        "id": 3,
        "description": "Find interesting trivia facts about the number 42.",
        "domain": "technology",
        "required_inputs": []
    }
]
}